Workbook

Sheet Read Me
B2: HOUSING CT, PREFAB MODULAR TEAM: city models and deck charts
B7: TABS
B8: Inputs Snapshot: every explorer input as it was set at export, for each city, with its status (sourced, placeholder, team choice) and note.
B9: Hartford / New Haven / Waterbury: one building per city. Sections: 1 scenario, 2 city data, 3 key assumptions, 4 calculations (cost, rent, buyer capacity),
B10: 5 results incl. both gaps, the funding stack and the owner's net monthly cost, 6 uses vs. sources, 7 funding waterfall, 8 owner-income sensitivity, 9 building size, 10 what moves the remaining gap.
B11: Compare: the three cities side by side (linked to the city tabs).
B12: Market Data: renter households by income band and the city profiles; rows the explorer controls (AMI, rents, sales, rent limit) come from the export.
B13: Charts: the deck charts as native Excel charts, fed by data blocks linked to the other tabs.
B15: WHERE THE NUMBERS COME FROM
B16: Every result is calculated by Prefab Gap Explorer 2 with the inputs set the way they were at export, including any city-only overrides. The Compare and Charts tabs link to the city tabs.
B17: This workbook is a presentation snapshot: the city tabs hold values, not formulas. For the fully live model with every formula, use 'Download Excel model' in the explorer's Export dialog.
B19: HOW THE MODEL WORKS
... B26: CHANGES FROM THE EXPLORER DEFAULTS

Sheet Inputs Snapshot
B2: INPUTS SNAPSHOT: every explorer input at export
B3: Values shown as the explorer formats them. "City only" marks a value set for one city.
B5: Input | C5: Group | D5: Hartford | E5: New Haven | F5: Waterbury | G5: Status | H5: Note

Sheet Hartford
B2: HARTFORD: one building, prefab modular
B5: 1. SCENARIO
B6: City
B7: Building design
B8: Total units in the building | C8: 0
B9: Owner unit bedrooms
B10: Rental unit bedrooms
B11: Owner household income target | C11: 0 | E11: % of AMI
B12: Owner household size | C12: 0
B13: Rental unit rent target | C13: 0 | E13: % of AMI; 0% = market rent
B14: Cap the AMI rent at market rent?
B15: Construction method
B16: Order volume (buildings ordered together) | C16: 0
B17: Appraisal basis
B18: Property tax assessed on
B20: 2. CITY DATA
B21: HUD 50% income limit, 4-person | C21: 0 | E21: HUD FY2026 Section 8 limits
B22: 100% AMI used in the model (2 x 50% limit) | C22: 0
B23: Bedrooms | C23: Studio | D23: 1BR | E23: 2BR | F23: 3BR | G23: 4BR
B24: Market asking rent by bedroom count ($ per month) | C24: 0 | D24: 0 | E24: 0 | F24: 0 | G24: 0
B25: Building size | C25: 2-unit | D25: 3-unit | E25: 4-6 unit
B26: Median sale, existing buildings (CT CAMA 2023-26) | C26: 0 | D26: 0 | E26: 0
B27: Size-adjusted new-build value (base case) | C27: 0
B28: DOH new-build precedent | C28: 0
B29: Assessment ratio used | C29: 0
B30: Mill rate | C30: 0 | E30: $ per $1,000 assessed
B31: Effective property tax rate | C31: 0
B32: Homeowner insurance ($ per unit per year) | C32: 0
B33: Land acquisition and closing ($ per building) | C33: 0
B35: 3. KEY ASSUMPTIONS (full list on Inputs Snapshot)
B36: Mortgage rate | C36: 0
B37: Mortgage term (years) | C37: 0
B38: Down payment | C38: 0
B39: FHA mortgage insurance (annual) | C39: 0
B40: Lender credit on rental income | C40: 0
B41: Lender test cap, % of qualifying income | C41: 0
B42: Owner test cap, % of own income | C42: 0
B43: Rent + utilities as % of renter income | C43: 0
B44: Tenant utility allowance (rental unit) | C44: 0
B45: Vacancy and collection loss | C45: 0
B46: Maintenance and reserve (% of value per year) | C46: 0
B47: Owner energy bills ($ per month) | C47: 0
... B53: Developer fee (% of cost) | C53: 0
B55: 4. CALCULATIONS
B56: Building and development cost
B57: Owner unit net sq ft | C57: 0
B58: Rental unit net sq ft (each) | C58: 0
B59: Rented units | C59: 0
B60: Gross sq ft, whole building | C60: 0
B61: Factory cost per gross sq ft (at this order volume) | C61: 0
B62: Field cost per gross sq ft | C62: 0
B63: Transport, crane and set | C63: 0
B64: Building (factory + field + transport, or stick-built) | C64: 0
B65: Add-ons and hard-cost extras | C65: 0
B66: Warehouse and bulk buying (net) | C66: 0
B67: Site work | C67: 0
B68: Hard-cost contingency | C68: 0
... B76: TDC per gross sq ft | C76: 0
B78: Rent for the rental unit
B79: Renter household income at the rent target | C79: 0
B80: AMI rent, net of utilities (what the owner can charge) | C80: 0
B81: Market asking rent, rental bedroom count | C81: 0
B82: Rent charged per rental unit | C82: 0
B83: What sets the rent
B84: Rent charged as % of renter income | C84: 0
B85: Gross rent, all rental units, per month | C85: 0
B86: Rent collected per month (after vacancy) | C86: 0
B87: Rent a lender counts, per month | C87: 0
B89: What the buyer can pay
B90: Owner household income | C90: 0
B91: Property tax per month | C91: 0
B92: Insurance per month | C92: 0
B93: Owner-paid common utilities per month | C93: 0
B94: Owner energy bills per month | C94: 0
B95: Maintenance and reserve per month | C95: 0
B96: Less add-on savings per month | C96: 0
B97: Non-mortgage housing costs per month | C97: 0
B98: Monthly payment per $1 of loan (P&I + FHA insurance) | C98: 0
B99: Lender test: maximum price | C99: 0
B100: Owner test: maximum price | C100: 0
B101: Buyer capacity (lower of the two tests) | C101: 0
B102: Which test binds
B103: CHFA Time To Own and other buyer assistance | C103: 0
B104: Most the buyer can pay | C104: 0
B106: 5. RESULTS
B107: Appraised value | C107: 0
B108: Sales gap (appraisal − what the buyer can pay) | C108: 0
B109: DOH homebuyer subsidy | C109: 0
B110: Sale proceeds to the developer | C110: 0
B111: What the buyer pays (mortgage + down payment) | C111: 0
B112: Developer gap (TDC − sale proceeds) | C112: 0
B113: HDF / C4C grant | C113: 0
B114: FHLBank Boston AHP | C114: 0
B115: HTCC share | C115: 0
B116: New Markets Tax Credits (net, if on) | C116: 0
B117: DOH developer subsidy | C117: 0
B118: Remaining developer gap | C118: 0
... B122: Most the buyer can pay as % of the existing-building median | C122: 0
B124: Owner's net monthly housing cost
B125: Mortgage payment + FHA insurance | C125: 0
...

Sheet New Haven
B2: NEW HAVEN: one building, prefab modular
B5: 1. SCENARIO
B6: City
B7: Building design
B8: Total units in the building | C8: 0
B9: Owner unit bedrooms
B10: Rental unit bedrooms
B11: Owner household income target | C11: 0 | E11: % of AMI
B12: Owner household size | C12: 0
B13: Rental unit rent target | C13: 0 | E13: % of AMI; 0% = market rent
B14: Cap the AMI rent at market rent?
B15: Construction method
B16: Order volume (buildings ordered together) | C16: 0
B17: Appraisal basis
B18: Property tax assessed on
B20: 2. CITY DATA
B21: HUD 50% income limit, 4-person | C21: 0 | E21: HUD FY2026 Section 8 limits
B22: 100% AMI used in the model (2 x 50% limit) | C22: 0
B23: Bedrooms | C23: Studio | D23: 1BR | E23: 2BR | F23: 3BR | G23: 4BR
B24: Market asking rent by bedroom count ($ per month) | C24: 0 | D24: 0 | E24: 0 | F24: 0 | G24: 0
B25: Building size | C25: 2-unit | D25: 3-unit | E25: 4-6 unit
B26: Median sale, existing buildings (CT CAMA 2023-26) | C26: 0 | D26: 0 | E26: 0
B27: Size-adjusted new-build value (base case) | C27: 0
B28: DOH new-build precedent | C28: 0
B29: Assessment ratio used | C29: 0
B30: Mill rate | C30: 0 | E30: $ per $1,000 assessed
B31: Effective property tax rate | C31: 0
B32: Homeowner insurance ($ per unit per year) | C32: 0
B33: Land acquisition and closing ($ per building) | C33: 0
B35: 3. KEY ASSUMPTIONS (full list on Inputs Snapshot)
B36: Mortgage rate | C36: 0
B37: Mortgage term (years) | C37: 0
B38: Down payment | C38: 0
B39: FHA mortgage insurance (annual) | C39: 0
B40: Lender credit on rental income | C40: 0
B41: Lender test cap, % of qualifying income | C41: 0
B42: Owner test cap, % of own income | C42: 0
B43: Rent + utilities as % of renter income | C43: 0
B44: Tenant utility allowance (rental unit) | C44: 0
B45: Vacancy and collection loss | C45: 0
B46: Maintenance and reserve (% of value per year) | C46: 0
B47: Owner energy bills ($ per month) | C47: 0
... B53: Developer fee (% of cost) | C53: 0
B55: 4. CALCULATIONS
B56: Building and development cost
B57: Owner unit net sq ft | C57: 0
B58: Rental unit net sq ft (each) | C58: 0
B59: Rented units | C59: 0
B60: Gross sq ft, whole building | C60: 0
B61: Factory cost per gross sq ft (at this order volume) | C61: 0
B62: Field cost per gross sq ft | C62: 0
B63: Transport, crane and set | C63: 0
B64: Building (factory + field + transport, or stick-built) | C64: 0
B65: Add-ons and hard-cost extras | C65: 0
B66: Warehouse and bulk buying (net) | C66: 0
B67: Site work | C67: 0
B68: Hard-cost contingency | C68: 0
... B76: TDC per gross sq ft | C76: 0
B78: Rent for the rental unit
B79: Renter household income at the rent target | C79: 0
B80: AMI rent, net of utilities (what the owner can charge) | C80: 0
B81: Market asking rent, rental bedroom count | C81: 0
B82: Rent charged per rental unit | C82: 0
B83: What sets the rent
B84: Rent charged as % of renter income | C84: 0
B85: Gross rent, all rental units, per month | C85: 0
B86: Rent collected per month (after vacancy) | C86: 0
B87: Rent a lender counts, per month | C87: 0
B89: What the buyer can pay
B90: Owner household income | C90: 0
B91: Property tax per month | C91: 0
B92: Insurance per month | C92: 0
B93: Owner-paid common utilities per month | C93: 0
B94: Owner energy bills per month | C94: 0
B95: Maintenance and reserve per month | C95: 0
B96: Less add-on savings per month | C96: 0
B97: Non-mortgage housing costs per month | C97: 0
B98: Monthly payment per $1 of loan (P&I + FHA insurance) | C98: 0
B99: Lender test: maximum price | C99: 0
B100: Owner test: maximum price | C100: 0
B101: Buyer capacity (lower of the two tests) | C101: 0
B102: Which test binds
B103: CHFA Time To Own and other buyer assistance | C103: 0
B104: Most the buyer can pay | C104: 0
B106: 5. RESULTS
B107: Appraised value | C107: 0
B108: Sales gap (appraisal − what the buyer can pay) | C108: 0
B109: DOH homebuyer subsidy | C109: 0
B110: Sale proceeds to the developer | C110: 0
B111: What the buyer pays (mortgage + down payment) | C111: 0
B112: Developer gap (TDC − sale proceeds) | C112: 0
B113: HDF / C4C grant | C113: 0
B114: FHLBank Boston AHP | C114: 0
B115: HTCC share | C115: 0
B116: New Markets Tax Credits (net, if on) | C116: 0
B117: DOH developer subsidy | C117: 0
B118: Remaining developer gap | C118: 0
... B122: Most the buyer can pay as % of the existing-building median | C122: 0
B124: Owner's net monthly housing cost
B125: Mortgage payment + FHA insurance | C125: 0
...

Sheet Waterbury
B2: WATERBURY: one building, prefab modular
B5: 1. SCENARIO
B6: City
B7: Building design
B8: Total units in the building | C8: 0
B9: Owner unit bedrooms
B10: Rental unit bedrooms
B11: Owner household income target | C11: 0 | E11: % of AMI
B12: Owner household size | C12: 0
B13: Rental unit rent target | C13: 0 | E13: % of AMI; 0% = market rent
B14: Cap the AMI rent at market rent?
B15: Construction method
B16: Order volume (buildings ordered together) | C16: 0
B17: Appraisal basis
B18: Property tax assessed on
B20: 2. CITY DATA
B21: HUD 50% income limit, 4-person | C21: 0 | E21: HUD FY2026 Section 8 limits
B22: 100% AMI used in the model (2 x 50% limit) | C22: 0
B23: Bedrooms | C23: Studio | D23: 1BR | E23: 2BR | F23: 3BR | G23: 4BR
B24: Market asking rent by bedroom count ($ per month) | C24: 0 | D24: 0 | E24: 0 | F24: 0 | G24: 0
B25: Building size | C25: 2-unit | D25: 3-unit | E25: 4-6 unit
B26: Median sale, existing buildings (CT CAMA 2023-26) | C26: 0 | D26: 0 | E26: 0
B27: Size-adjusted new-build value (base case) | C27: 0
B28: DOH new-build precedent | C28: 0
B29: Assessment ratio used | C29: 0
B30: Mill rate | C30: 0 | E30: $ per $1,000 assessed
B31: Effective property tax rate | C31: 0
B32: Homeowner insurance ($ per unit per year) | C32: 0
B33: Land acquisition and closing ($ per building) | C33: 0
B35: 3. KEY ASSUMPTIONS (full list on Inputs Snapshot)
B36: Mortgage rate | C36: 0
B37: Mortgage term (years) | C37: 0
B38: Down payment | C38: 0
B39: FHA mortgage insurance (annual) | C39: 0
B40: Lender credit on rental income | C40: 0
B41: Lender test cap, % of qualifying income | C41: 0
B42: Owner test cap, % of own income | C42: 0
B43: Rent + utilities as % of renter income | C43: 0
B44: Tenant utility allowance (rental unit) | C44: 0
B45: Vacancy and collection loss | C45: 0
B46: Maintenance and reserve (% of value per year) | C46: 0
B47: Owner energy bills ($ per month) | C47: 0
... B53: Developer fee (% of cost) | C53: 0
B55: 4. CALCULATIONS
B56: Building and development cost
B57: Owner unit net sq ft | C57: 0
B58: Rental unit net sq ft (each) | C58: 0
B59: Rented units | C59: 0
B60: Gross sq ft, whole building | C60: 0
B61: Factory cost per gross sq ft (at this order volume) | C61: 0
B62: Field cost per gross sq ft | C62: 0
B63: Transport, crane and set | C63: 0
B64: Building (factory + field + transport, or stick-built) | C64: 0
B65: Add-ons and hard-cost extras | C65: 0
B66: Warehouse and bulk buying (net) | C66: 0
B67: Site work | C67: 0
B68: Hard-cost contingency | C68: 0
... B76: TDC per gross sq ft | C76: 0
B78: Rent for the rental unit
B79: Renter household income at the rent target | C79: 0
B80: AMI rent, net of utilities (what the owner can charge) | C80: 0
B81: Market asking rent, rental bedroom count | C81: 0
B82: Rent charged per rental unit | C82: 0
B83: What sets the rent
B84: Rent charged as % of renter income | C84: 0
B85: Gross rent, all rental units, per month | C85: 0
B86: Rent collected per month (after vacancy) | C86: 0
B87: Rent a lender counts, per month | C87: 0
B89: What the buyer can pay
B90: Owner household income | C90: 0
B91: Property tax per month | C91: 0
B92: Insurance per month | C92: 0
B93: Owner-paid common utilities per month | C93: 0
B94: Owner energy bills per month | C94: 0
B95: Maintenance and reserve per month | C95: 0
B96: Less add-on savings per month | C96: 0
B97: Non-mortgage housing costs per month | C97: 0
B98: Monthly payment per $1 of loan (P&I + FHA insurance) | C98: 0
B99: Lender test: maximum price | C99: 0
B100: Owner test: maximum price | C100: 0
B101: Buyer capacity (lower of the two tests) | C101: 0
B102: Which test binds
B103: CHFA Time To Own and other buyer assistance | C103: 0
B104: Most the buyer can pay | C104: 0
B106: 5. RESULTS
B107: Appraised value | C107: 0
B108: Sales gap (appraisal − what the buyer can pay) | C108: 0
B109: DOH homebuyer subsidy | C109: 0
B110: Sale proceeds to the developer | C110: 0
B111: What the buyer pays (mortgage + down payment) | C111: 0
B112: Developer gap (TDC − sale proceeds) | C112: 0
B113: HDF / C4C grant | C113: 0
B114: FHLBank Boston AHP | C114: 0
B115: HTCC share | C115: 0
B116: New Markets Tax Credits (net, if on) | C116: 0
B117: DOH developer subsidy | C117: 0
B118: Remaining developer gap | C118: 0
... B122: Most the buyer can pay as % of the existing-building median | C122: 0
B124: Owner's net monthly housing cost
B125: Mortgage payment + FHA insurance | C125: 0
...

Sheet Compare
B2: THREE-CITY COMPARISON (linked to the city tabs)
C4: Hartford | D4: New Haven | E4: Waterbury
B5: Building design | C5: =Hartford!$C$7 | D5: ='New Haven'!$C$7 | E5: =Waterbury!$C$7
B6: Owner income at target AMI | C6: =Hartford!$C$90 | D6: ='New Haven'!$C$90 | E6: =Waterbury!$C$90
B7: Most the buyer can pay | C7: =Hartford!$C$104 | D7: ='New Haven'!$C$104 | E7: =Waterbury!$C$104
B8: Appraised value | C8: =Hartford!$C$107 | D8: ='New Haven'!$C$107 | E8: =Waterbury!$C$107
B9: Most the buyer can pay as % of the existing-building median | C9: =Hartford!$C$122 | D9: ='New Haven'!$C$122 | E9: =Waterbury!$C$122
B10: Sales gap | C10: =Hartford!$C$108 | D10: ='New Haven'!$C$108 | E10: =Waterbury!$C$108
B11: Owner's net monthly cost (after rent received) | C11: =Hartford!$C$129 | D11: ='New Haven'!$C$129 | E11: =Waterbury!$C$129
B12: Net cost as % of owner income | C12: =Hartford!$C$130 | D12: ='New Haven'!$C$130 | E12: =Waterbury!$C$130
B13: Rent charged, rental unit | C13: =Hartford!$C$82 | D13: ='New Haven'!$C$82 | E13: =Waterbury!$C$82
B14: Market asking rent, rental unit | C14: =Hartford!$C$81 | D14: ='New Haven'!$C$81 | E14: =Waterbury!$C$81
B15: Total development cost | C15: =Hartford!$C$74 | D15: ='New Haven'!$C$74 | E15: =Waterbury!$C$74
B16: TDC per unit | C16: =Hartford!$C$75 | D16: ='New Haven'!$C$75 | E16: =Waterbury!$C$75
B17: Developer gap | C17: =Hartford!$C$112 | D17: ='New Haven'!$C$112 | E17: =Waterbury!$C$112
B18: Remaining developer gap | C18: =Hartford!$C$118 | D18: ='New Haven'!$C$118 | E18: =Waterbury!$C$118
B19: Total subsidy needed | C19: =Hartford!$C$119 | D19: ='New Haven'!$C$119 | E19: =Waterbury!$C$119
B20: Subsidy needed per unit | C20: =Hartford!$C$120 | D20: ='New Haven'!$C$120 | E20: =Waterbury!$C$120

Sheet Market Data
B2: MARKET DATA: renter households by income band, 2024
B3: Source: team AMI Distribution Analysis (ACS 2024 1-year B25118 renter households by income, HUD FY2024 3-person limits, incomes spread evenly within brackets). Counts are estimates with ACS margins of error.
B5: Renter households | C5: Under 30% AMI | D5: 30-50% AMI | E5: 50-80% AMI | F5: 80-100% AMI | G5: Over 100% AMI | H5: Total
B6: Hartford | C6: 16254 | D6: 6026 | E6: 6832 | F6: 2875 | G6: 4437 | H6: =SUM(C6:G6)
B7: New Haven | C7: 12538 | D7: 8612 | E7: 6594 | F7: 3329 | G7: 8313 | H7: =SUM(C7:G7)
B8: Waterbury | C8: 12085 | D8: 5163 | E8: 4078 | F8: 755 | G8: 1542 | H8: =SUM(C8:G8)
B10: Share of renter households | C10: Under 30% AMI | D10: 30-50% AMI | E10: 50-80% AMI | F10: 80-100% AMI | G10: Over 100% AMI
B11: Hartford | C11: =C6/$H6 | D11: =D6/$H6 | E11: =E6/$H6 | F11: =F6/$H6 | G11: =G6/$H6
B12: New Haven | C12: =C7/$H7 | D12: =D7/$H7 | E12: =E7/$H7 | F12: =F7/$H7 | G12: =G7/$H7
B13: Waterbury | C13: =C8/$H8 | D13: =D8/$H8 | E13: =E8/$H8 | F13: =F8/$H8 | G13: =G8/$H8
B16: CITY PROFILES (deck: 'Three cities, three markets' slide)
B17: Sources: Census QuickFacts V2025; ACS 2024 1-year (homeownership B25118, median income B19013, poverty); Zillow asking rents Sept 2026 (New Haven) and Redfin Aug 2026; CT CAMA 2023-26; team AMI analysis. Rows marked "explorer" come from the export.
B18: Metric | C18: Hartford | D18: New Haven | E18: Waterbury | F18: From
B19: Population, July 2025 | C19: 121981 | D19: 138774 | E19: 115771 | F19: static
B20: Population change since 2020 | C20: 0.003 | D20: 0.036 | E20: 0.012 | F20: static
B21: Homeownership rate | C21: 0.26 | D21: 0.3 | E21: 0.46 | F21: static
B22: Median household income (city) | C22: 50418 | D22: 59705 | E22: 47881 | F22: static
B23: Area median income, 4-person (HUD published) | C23: 129200 | D23: 123200 | E23: 114000 | F23: static
B24: 60% AMI, 4-person (model: 2 x 50% limit x 0.6) | C24: 0 | D24: 0 | E24: 0 | F24: explorer
B25: 80% AMI, 4-person (model) | C25: 0 | D25: 0 | E25: 0 | F25: explorer
B26: Asking rent, 1BR | C26: 0 | D26: 0 | E26: 0 | F26: explorer
B27: Asking rent, 2BR | C27: 0 | D27: 0 | E27: 0 | F27: explorer
B28: Asking rent, 3BR | C28: 0 | D28: 0 | E28: 0 | F28: explorer
B29: 60% AMI rent limit, 2BR (gross, rent + utilities) | C29: 0 | D29: 0 | E29: 0 | F29: explorer
B30: Median sale price, all homes (Redfin) | C30: 339775 | D30: 399735 | E30: 309795 | F30: static
... B37: Income needed to buy the median home (% of AMI) | C37: 1.16 | D37: 1.2 | E37: 1.15 | F37: static
B38: Market role | C38: Deep-need rental | D38: Growing, high-revenue | E38: Ownership city | F38: static
B39: City median income as % of AMI | C39: =C22/C23 | D39: =D22/D23 | E39: =E22/E23

Sheet Charts
B2: CHARTS: native Excel charts for the deck. Data blocks link to the city tabs and Market Data.
B3: To keep a chart linked in PowerPoint: copy it here and use Paste Special > 'Use Destination Theme & Link Data'. Right-click any series to recolor it.
B5: A. Most a buyer can pay vs. the appraisal, by owner income (deck: affordability curve)
B6: Owner income, % of AMI | C6: ='New Haven'!C170 | D6: ='New Haven'!D170 | E6: ='New Haven'!E170 | F6: ='New Haven'!F170 | G6: ='New Haven'!G170 | H6: ='New Haven'!H170 | I6: ='New Haven'!I170
B7: Hartford: most the buyer can pay | C7: =Hartford!C174 | D7: =Hartford!D174 | E7: =Hartford!E174 | F7: =Hartford!F174 | G7: =Hartford!G174 | H7: =Hartford!H174 | I7: =Hartford!I174
B8: Hartford: appraised value | C8: =Hartford!C175 | D8: =Hartford!D175 | E8: =Hartford!E175 | F8: =Hartford!F175 | G8: =Hartford!G175 | H8: =Hartford!H175 | I8: =Hartford!I175
B9: New Haven: most the buyer can pay | C9: ='New Haven'!C174 | D9: ='New Haven'!D174 | E9: ='New Haven'!E174 | F9: ='New Haven'!F174 | G9: ='New Haven'!G174 | H9: ='New Haven'!H174 | I9: ='New Haven'!I174
B10: New Haven: appraised value | C10: ='New Haven'!C175 | D10: ='New Haven'!D175 | E10: ='New Haven'!E175 | F10: ='New Haven'!F175 | G10: ='New Haven'!G175 | H10: ='New Haven'!H175 | I10: ='New Haven'!I175
B11: Waterbury: most the buyer can pay | C11: =Waterbury!C174 | D11: =Waterbury!D174 | E11: =Waterbury!E174 | F11: =Waterbury!F174 | G11: =Waterbury!G174 | H11: =Waterbury!H174 | I11: =Waterbury!I174
B12: Waterbury: appraised value | C12: =Waterbury!C175 | D12: =Waterbury!D175 | E12: =Waterbury!E175 | F12: =Waterbury!F175 | G12: =Waterbury!G175 | H12: =Waterbury!H175 | I12: =Waterbury!I175
B33: B. Renter households by income band, 2024 (deck: buyer pool)
B34: City | C34: Under 30% AMI | D34: 30-50% AMI | E34: 50-80% AMI | F34: 80-100% AMI | G34: Over 100% AMI
B35: ='Market Data'!B11 | C35: ='Market Data'!C11 | D35: ='Market Data'!D11 | E35: ='Market Data'!E11 | F35: ='Market Data'!F11 | G35: ='Market Data'!G11
B36: ='Market Data'!B12 | C36: ='Market Data'!C12 | D36: ='Market Data'!D12 | E36: ='Market Data'!E12 | F36: ='Market Data'!F12 | G36: ='Market Data'!G12
B37: ='Market Data'!B13 | C37: ='Market Data'!C13 | D37: ='Market Data'!D13 | E37: ='Market Data'!E13 | F37: ='Market Data'!F13 | G37: ='Market Data'!G13
B57: C. Uses vs. sources, one Hartford building (deck: city model)
C58: Uses | D58: Sources
B59: =Hartford!B136 | C59: =Hartford!C136 | D59: =Hartford!D136
B60: =Hartford!B137 | C60: =Hartford!C137 | D60: =Hartford!D137
B61: =Hartford!B138 | C61: =Hartford!C138 | D61: =Hartford!D138
B62: =Hartford!B139 | C62: =Hartford!C139 | D62: =Hartford!D139
B63: =Hartford!B140 | C63: =Hartford!C140 | D63: =Hartford!D140
B64: =Hartford!B141 | C64: =Hartford!C141 | D64: =Hartford!D141
B65: =Hartford!B142 | C65: =Hartford!C142 | D65: =Hartford!D142
B66: =Hartford!B143 | C66: =Hartford!C143 | D66: =Hartford!D143
B67: =Hartford!B144 | C67: =Hartford!C144 | D67: =Hartford!D144
B68: =Hartford!B145 | C68: =Hartford!C145 | D68: =Hartford!D145
B69: =Hartford!B146 | C69: =Hartford!C146 | D69: =Hartford!D146
B70: =Hartford!B147 | C70: =Hartford!C147 | D70: =Hartford!D147
... B74: =Hartford!B151 | C74: =Hartford!C151 | D74: =Hartford!D151
B79: C. Uses vs. sources, one New Haven building (deck: city model)
C80: Uses | D80: Sources
B81: ='New Haven'!B136 | C81: ='New Haven'!C136 | D81: ='New Haven'!D136
B82: ='New Haven'!B137 | C82: ='New Haven'!C137 | D82: ='New Haven'!D137
B83: ='New Haven'!B138 | C83: ='New Haven'!C138 | D83: ='New Haven'!D138
B84: ='New Haven'!B139 | C84: ='New Haven'!C139 | D84: ='New Haven'!D139
B85: ='New Haven'!B140 | C85: ='New Haven'!C140 | D85: ='New Haven'!D140
B86: ='New Haven'!B141 | C86: ='New Haven'!C141 | D86: ='New Haven'!D141
B87: ='New Haven'!B142 | C87: ='New Haven'!C142 | D87: ='New Haven'!D142
B88: ='New Haven'!B143 | C88: ='New Haven'!C143 | D88: ='New Haven'!D143
B89: ='New Haven'!B144 | C89: ='New Haven'!C144 | D89: ='New Haven'!D144
B90: ='New Haven'!B145 | C90: ='New Haven'!C145 | D90: ='New Haven'!D145
B91: ='New Haven'!B146 | C91: ='New Haven'!C146 | D91: ='New Haven'!D146
B92: ='New Haven'!B147 | C92: ='New Haven'!C147 | D92: ='New Haven'!D147
... B96: ='New Haven'!B151 | C96: ='New Haven'!C151 | D96: ='New Haven'!D151
B101: C. Uses vs. sources, one Waterbury building (deck: city model)
C102: Uses | D102: Sources
B103: =Waterbury!B136 | C103: =Waterbury!C136 | D103: =Waterbury!D136
B104: =Waterbury!B137 | C104: =Waterbury!C137 | D104: =Waterbury!D137
B105: =Waterbury!B138 | C105: =Waterbury!C138 | D105: =Waterbury!D138
B106: =Waterbury!B139 | C106: =Waterbury!C139 | D106: =Waterbury!D139
B107: =Waterbury!B140 | C107: =Waterbury!C140 | D107: =Waterbury!D140
B108: =Waterbury!B141 | C108: =Waterbury!C141 | D108: =Waterbury!D141
B109: =Waterbury!B142 | C109: =Waterbury!C142 | D109: =Waterbury!D142
B110: =Waterbury!B143 | C110: =Waterbury!C143 | D110: =Waterbury!D143
B111: =Waterbury!B144 | C111: =Waterbury!C144 | D111: =Waterbury!D144
B112: =Waterbury!B145 | C112: =Waterbury!C145 | D112: =Waterbury!D145
B113: =Waterbury!B146 | C113: =Waterbury!C146 | D113: =Waterbury!D146
B114: =Waterbury!B147 | C114: =Waterbury!C147 | D114: =Waterbury!D147
... B118: =Waterbury!B151 | C118: =Waterbury!C151 | D118: =Waterbury!D151
B123: D. TDC per unit, modular vs. stick-built (New Haven tab; deck: modular vs. stick)
B124: Building size | C124: ='New Haven'!C183&" units" | D124: ='New Haven'!D183&" units" | E124: ='New Haven'!E183&" units"
B125: Modular | C125: ='New Haven'!C186 | D125: ='New Haven'!D186 | E125: ='New Haven'!E186
B126: Stick-built | C126: ='New Haven'!C188 | D126: ='New Haven'!D188 | E126: ='New Haven'!E188
B127: Modular saving | C127: ='New Haven'!C189 | D127: ='New Haven'!D189 | E127: ='New Haven'!E189
B128: Modular subsidy needed per unit | C128: ='New Haven'!C191 | D128: ='New Haven'!D191 | E128: ='New Haven'!E191
B145: E. Funding waterfall, one Hartford building (caps, not awards; deck: funding stack)
C146: Base (hidden) | D146: Amount
B147: =Hartford!B157 | C147: =Hartford!D157 | D147: =Hartford!E157
B148: =Hartford!B158 | C148: =Hartford!D158 | D148: =Hartford!E158
B149: =Hartford!B159 | C149: =Hartford!D159 | D149: =Hartford!E159
B150: =Hartford!B160 | C150: =Hartford!D160 | D150: =Hartford!E160
B151: =Hartford!B161 | C151: =Hartford!D161 | D151: =Hartford!E161
B152: =Hartford!B162 | C152: =Hartford!D162 | D152: =Hartford!E162
B153: =Hartford!B163 | C153: =Hartford!D163 | D153: =Hartford!E163
B154: =Hartford!B164 | C154: =Hartford!D164 | D154: =Hartford!E164
B155: =Hartford!B165 | C155: =Hartford!D165 | D155: =Hartford!E165
B156: =Hartford!B166 | C156: =Hartford!D166 | D156: =Hartford!E166
B166: E. Funding waterfall, one New Haven building (caps, not awards; deck: funding stack)
C167: Base (hidden) | D167: Amount
B168: ='New Haven'!B157 | C168: ='New Haven'!D157 | D168: ='New Haven'!E157
B169: ='New Haven'!B158 | C169: ='New Haven'!D158 | D169: ='New Haven'!E158
B170: ='New Haven'!B159 | C170: ='New Haven'!D159 | D170: ='New Haven'!E159
B171: ='New Haven'!B160 | C171: ='New Haven'!D160 | D171: ='New Haven'!E160
B172: ='New Haven'!B161 | C172: ='New Haven'!D161 | D172: ='New Haven'!E161
B173: ='New Haven'!B162 | C173: ='New Haven'!D162 | D173: ='New Haven'!E162
B174: ='New Haven'!B163 | C174: ='New Haven'!D163 | D174: ='New Haven'!E163
B175: ='New Haven'!B164 | C175: ='New Haven'!D164 | D175: ='New Haven'!E164
B176: ='New Haven'!B165 | C176: ='New Haven'!D165 | D176: ='New Haven'!E165
B177: ='New Haven'!B166 | C177: ='New Haven'!D166 | D177: ='New Haven'!E166
B187: E. Funding waterfall, one Waterbury building (caps, not awards; deck: funding stack)
C188: Base (hidden) | D188: Amount
B189: =Waterbury!B157 | C189: =Waterbury!D157 | D189: =Waterbury!E157
B190: =Waterbury!B158 | C190: =Waterbury!D158 | D190: =Waterbury!E158
B191: =Waterbury!B159 | C191: =Waterbury!D159 | D191: =Waterbury!E159
B192: =Waterbury!B160 | C192: =Waterbury!D160 | D192: =Waterbury!E160
B193: =Waterbury!B161 | C193: =Waterbury!D161 | D193: =Waterbury!E161
B194: =Waterbury!B162 | C194: =Waterbury!D162 | D194: =Waterbury!E162
B195: =Waterbury!B163 | C195: =Waterbury!D163 | D195: =Waterbury!E163
B196: =Waterbury!B164 | C196: =Waterbury!D164 | D196: =Waterbury!E164
...
